callable_tm/__init__.py
callable_tm/callable_tm.py
callable_tm-0.1.0.dist-info/LICENSE
callable_tm-0.1.0.dist-info/METADATA
callable_tm-0.1.0.dist-info/WHEEL
callable_tm-0.1.0.dist-info/top_level.txt
callable_tm-0.1.0.dist-info/RECORD
